{
  "resourceType": "SearchParameter",
  "id": "searchparameter-location-organization",
  "url": "http://hl7.org/fhir/ig/vhdir/SearchParameter/searchparameter-location-organization",
  "version": "0.0.0",
  "name": "VHDir Location Organization Search Parameter",
  "derivedFrom": "http://hl7.org/fhir/SearchParameter/Location-organization",
  "status": "draft",
  "date": "2018-05-23",
  "publisher": "HL7 Patient Administration Committee",
  "contact": [
    {
      "telecom": [
        {
          "system": "url",
          "value": "http://www.hl7.org/Special/committees/pafm/index.cfm"
        }
      ]
    }
  ],
  "code": "organization",
  "base": [
    "Location"
  ],
  "type": "reference",
  "description": "Searches for locations that are managed by the provided organization",
  "expression": "Location.managingOrganization",
  "target": [
    "Organization"
  ],
  "modifier": [
    "above",
    "below"
  ],
  "chain": [
    "identifier",
    "name",
    "address",
    "partof",
    "type"
  ]
}