
{
  "resourceType": "SearchParameter",
  "id": "searchparameter-verificationresult-target-location",
  "url": "http://hl7.org/fhir/uv/vhdir/SearchParameter/searchparameter-verificationresult-target-location",
  "version": "0.0.0",
  "name": "VHDir VerificationResult Target Location Search Parameter",
  "status": "draft",
  "date": "2018-05-23",
  "publisher": "HL7 Patient Administration Committee",
  "contact": [
    {
      "telecom": [
        {
          "system": "url",
          "value": "http://www.hl7.org/Special/committees/pafm/index.cfm"
        }
      ]
    }
  ],
  "code": "target-location",
  "base": ["VerificationResult"],
  "type": "string",
  "description": "Select validation information for the specified attribute of a resource",
  "expression": "VerificationResult.targetLocation",
  "multipleOr": true,
  "multipleAnd": true,
  "modifier": [
    "exact", "contains"
  ]
}